{
    "wolf": {
        "label": "wolf",
        "rune": null,
        "levels": {
            "1": {
                "hp_max": 43,
                "attack": 21
            },
            "2": {
                "hp_max": 65,
                "attack": 24
            },
            "3": {
                "hp_max": 90,
                "attack": 24
            },
            "4": {
                "hp_max": 114,
                "attack": 26
            },
            "5": {
                "hp_max": 147,
                "attack": 31
            },
            "6": {
                "hp_max": 170,
                "attack": 31
            },
            "7": {
                "hp_max": 196,
                "attack": 31
            },
            "8": {
                "hp_max": 221,
                "attack": 33
            },
            "9": {
                "hp_max": 245,
                "attack": 33
            },
            "10": {
                "hp_max": 277,
                "attack": 41
            },
            "11": {
                "hp_max": 298,
                "attack": 43
            },
            "12": {
                "hp_max": 322,
                "attack": 40
            },
            "13": {
                "hp_max": 345,
                "attack": 45
            },
            "14": {
                "hp_max": 371,
                "attack": 41
            },
            "15": {
                "hp_max": 401,
                "attack": 48
            },
            "16": {
                "hp_max": 427,
                "attack": 48
            },
            "17": {
                "hp_max": 450,
                "attack": 53
            },
            "18": {
                "hp_max": 475,
                "attack": 51
            },
            "19": {
                "hp_max": 499,
                "attack": 53
            },
            "20": {
                "hp_max": 531,
                "attack": 58
            },
            "21": {
                "hp_max": 552,
                "attack": 58
            },
            "22": {
                "hp_max": 576,
                "attack": 62
            },
            "23": {
                "hp_max": 601,
                "attack": 63
            },
            "24": {
                "hp_max": 626,
                "attack": 63
            },
            "25": {
                "hp_max": 658,
                "attack": 68
            },
            "26": {
                "hp_max": 681,
                "attack": 70
            },
            "27": {
                "hp_max": 707,
                "attack": 68
            },
            "28": {
                "hp_max": 731,
                "attack": 68
            },
            "29": {
                "hp_max": 756,
                "attack": 70
            },
            "30": {
                "hp_max": 788,
                "attack": 75
            },
            "31": {
                "hp_max": 809,
                "attack": 77
            },
            "32": {
                "hp_max": 831,
                "attack": 79
            },
            "33": {
                "hp_max": 858,
                "attack": 82
            },
            "34": {
                "hp_max": 881,
                "attack": 80
            },
            "35": {
                "hp_max": 912,
                "attack": 87
            },
            "36": {
                "hp_max": 936,
                "attack": 89
            },
            "37": {
                "hp_max": 963,
                "attack": 91
            },
            "38": {
                "hp_max": 985,
                "attack": 89
            },
            "39": {
                "hp_max": 1011,
                "attack": 92
            },
            "40": {
                "hp_max": 1043,
                "attack": 96
            },
            "41": {
                "hp_max": 1064,
                "attack": 96
            },
            "42": {
                "hp_max": 1089,
                "attack": 96
            },
            "43": {
                "hp_max": 1113,
                "attack": 97
            },
            "44": {
                "hp_max": 1138,
                "attack": 97
            },
            "45": {
                "hp_max": 1167,
                "attack": 108
            },
            "46": {
                "hp_max": 1194,
                "attack": 106
            },
            "47": {
                "hp_max": 1216,
                "attack": 106
            },
            "48": {
                "hp_max": 1243,
                "attack": 108
            },
            "49": {
                "hp_max": 1268,
                "attack": 109
            },
            "50": {
                "hp_max": 1298,
                "attack": 113
            }
        }
    },
    "skeleton": {
        "label": "skeleton",
        "rune": "fire",
        "levels": {
            "1": {
                "hp_max": 61,
                "attack": 12
            },
            "2": {
                "hp_max": 95,
                "attack": 12
            },
            "3": {
                "hp_max": 128,
                "attack": 13
            },
            "4": {
                "hp_max": 165,
                "attack": 14
            },
            "5": {
                "hp_max": 210,
                "attack": 18
            },
            "6": {
                "hp_max": 245,
                "attack": 18
            },
            "7": {
                "hp_max": 281,
                "attack": 20
            },
            "8": {
                "hp_max": 314,
                "attack": 20
            },
            "9": {
                "hp_max": 352,
                "attack": 17
            },
            "10": {
                "hp_max": 395,
                "attack": 24
            },
            "11": {
                "hp_max": 427,
                "attack": 25
            },
            "12": {
                "hp_max": 462,
                "attack": 21
            },
            "13": {
                "hp_max": 494,
                "attack": 26
            },
            "14": {
                "hp_max": 528,
                "attack": 24
            },
            "15": {
                "hp_max": 577,
                "attack": 26
            },
            "16": {
                "hp_max": 608,
                "attack": 27
            },
            "17": {
                "hp_max": 644,
                "attack": 27
            },
            "18": {
                "hp_max": 682,
                "attack": 29
            },
            "19": {
                "hp_max": 714,
                "attack": 31
            },
            "20": {
                "hp_max": 759,
                "attack": 34
            },
            "21": {
                "hp_max": 788,
                "attack": 35
            },
            "22": {
                "hp_max": 827,
                "attack": 34
            },
            "23": {
                "hp_max": 862,
                "attack": 36
            },
            "24": {
                "hp_max": 896,
                "attack": 37
            },
            "25": {
                "hp_max": 939,
                "attack": 41
            },
            "26": {
                "hp_max": 975,
                "attack": 40
            },
            "27": {
                "hp_max": 1012,
                "attack": 41
            },
            "28": {
                "hp_max": 1044,
                "attack": 42
            },
            "29": {
                "hp_max": 1078,
                "attack": 41
            },
            "30": {
                "hp_max": 1125,
                "attack": 46
            },
            "31": {
                "hp_max": 1156,
                "attack": 44
            },
            "32": {
                "hp_max": 1188,
                "attack": 43
            },
            "33": {
                "hp_max": 1225,
                "attack": 46
            },
            "34": {
                "hp_max": 1262,
                "attack": 46
            },
            "35": {
                "hp_max": 1303,
                "attack": 49
            },
            "36": {
                "hp_max": 1342,
                "attack": 51
            },
            "37": {
                "hp_max": 1376,
                "attack": 51
            },
            "38": {
                "hp_max": 1408,
                "attack": 53
            },
            "39": {
                "hp_max": 1445,
                "attack": 50
            },
            "40": {
                "hp_max": 1490,
                "attack": 56
            },
            "41": {
                "hp_max": 1519,
                "attack": 58
            },
            "42": {
                "hp_max": 1553,
                "attack": 58
            },
            "43": {
                "hp_max": 1590,
                "attack": 59
            },
            "44": {
                "hp_max": 1626,
                "attack": 56
            },
            "45": {
                "hp_max": 1671,
                "attack": 59
            },
            "46": {
                "hp_max": 1707,
                "attack": 60
            },
            "47": {
                "hp_max": 1742,
                "attack": 60
            },
            "48": {
                "hp_max": 1773,
                "attack": 61
            },
            "49": {
                "hp_max": 1808,
                "attack": 64
            },
            "50": {
                "hp_max": 1857,
                "attack": 64
            }
        }
    },
    "leonard": {
        "label": "leonard",
        "rune": null,
        "levels": {
            "1": {
                "hp_max": 1213,
                "attack": 4
            },
            "2": {
                "hp_max": 219,
                "attack": 20
            },
            "3": {
                "hp_max": 227,
                "attack": 24
            },
            "4": {
                "hp_max": 237,
                "attack": 35
            },
            "5": {
                "hp_max": 292,
                "attack": 44
            },
            "6": {
                "hp_max": 298,
                "attack": 47
            },
            "7": {
                "hp_max": 306,
                "attack": 56
            },
            "8": {
                "hp_max": 318,
                "attack": 65
            },
            "9": {
                "hp_max": 330,
                "attack": 71
            },
            "10": {
                "hp_max": 386,
                "attack": 81
            },
            "11": {
                "hp_max": 397,
                "attack": 83
            },
            "12": {
                "hp_max": 408,
                "attack": 93
            },
            "13": {
                "hp_max": 412,
                "attack": 98
            },
            "14": {
                "hp_max": 419,
                "attack": 108
            },
            "15": {
                "hp_max": 481,
                "attack": 113
            },
            "16": {
                "hp_max": 483,
                "attack": 122
            },
            "17": {
                "hp_max": 493,
                "attack": 129
            },
            "18": {
                "hp_max": 507,
                "attack": 135
            },
            "19": {
                "hp_max": 514,
                "attack": 143
            },
            "20": {
                "hp_max": 577,
                "attack": 151
            },
            "21": {
                "hp_max": 580,
                "attack": 160
            },
            "22": {
                "hp_max": 586,
                "attack": 165
            },
            "23": {
                "hp_max": 595,
                "attack": 173
            },
            "24": {
                "hp_max": 608,
                "attack": 179
            },
            "25": {
                "hp_max": 663,
                "attack": 188
            },
            "26": {
                "hp_max": 673,
                "attack": 193
            },
            "27": {
                "hp_max": 684,
                "attack": 200
            },
            "28": {
                "hp_max": 690,
                "attack": 211
            },
            "29": {
                "hp_max": 703,
                "attack": 218
            },
            "30": {
                "hp_max": 758,
                "attack": 223
            },
            "31": {
                "hp_max": 769,
                "attack": 229
            },
            "32": {
                "hp_max": 779,
                "attack": 237
            },
            "33": {
                "hp_max": 787,
                "attack": 243
            },
            "34": {
                "hp_max": 790,
                "attack": 250
            },
            "35": {
                "hp_max": 853,
                "attack": 260
            },
            "36": {
                "hp_max": 855,
                "attack": 268
            },
            "37": {
                "hp_max": 873,
                "attack": 275
            },
            "38": {
                "hp_max": 872,
                "attack": 281
            },
            "39": {
                "hp_max": 883,
                "attack": 289
            },
            "40": {
                "hp_max": 944,
                "attack": 300
            },
            "41": {
                "hp_max": 952,
                "attack": 306
            },
            "42": {
                "hp_max": 961,
                "attack": 313
            },
            "43": {
                "hp_max": 970,
                "attack": 316
            },
            "44": {
                "hp_max": 982,
                "attack": 326
            },
            "45": {
                "hp_max": 1041,
                "attack": 333
            },
            "46": {
                "hp_max": 1049,
                "attack": 339
            },
            "47": {
                "hp_max": 1058,
                "attack": 348
            },
            "48": {
                "hp_max": 1064,
                "attack": 353
            },
            "49": {
                "hp_max": 1068,
                "attack": 360
            },
            "50": {
                "hp_max": 1126,
                "attack": 372
            }
        }
    }
}